{
  "entityType" : "ENTITY_GROUP",
  "entity" : {
    "additionalInfo" : null,
    "configuration" : {
      "columns" : [ {
        "type" : "ENTITY_FIELD",
        "key" : "created_time",
        "sortOrder" : "DESC"
      }, {
        "type" : "ENTITY_FIELD",
        "key" : "first_name",
        "sortOrder" : "NONE"
      }, {
        "type" : "ENTITY_FIELD",
        "key" : "last_name",
        "sortOrder" : "NONE"
      }, {
        "type" : "ENTITY_FIELD",
        "key" : "email",
        "sortOrder" : "NONE"
      } ],
      "settings" : { },
      "actions" : { }
    },
    "edgeGroupAll" : false,
    "externalId" : null,
    "groupAll" : true,
    "id" : {
      "entityType" : "ENTITY_GROUP",
      "id" : "7d587120-2cbb-11f0-9608-914ec54dbe66"
    },
    "name" : "All",
    "ownerId" : {
      "entityType" : "CUSTOMER",
      "id" : "7d52cbd0-2cbb-11f0-9608-914ec54dbe66"
    },
    "type" : "USER"
  },
  "relations" : [ ],
  "attributes" : {
    "SERVER_SCOPE" : [ ]
  },
  "groupEntities" : true,
  "permissions" : [ ]
}